Gui_creater/__init__.py
Gui_creater/gui_creater.py
Gui_creater/gui_easily.py
Gui_creater/gui_savewidget.py
Gui_creater/upload.py
Gui_creater/widget_data.py
Gui_creater-0.1.2.dist-info/LICENSE
Gui_creater-0.1.2.dist-info/METADATA
Gui_creater-0.1.2.dist-info/WHEEL
Gui_creater-0.1.2.dist-info/top_level.txt
Gui_creater-0.1.2.dist-info/RECORD
