Metadata-Version: 2.2
Name: Gui_creater
Version: 0.1.2
Summary: A simple library to make useful Gui.
Home-page: https://github.com/pysilver-8888/Gui_creater
Author: pysilver
Author-email: 19595263@qq.com
License: MIT
Keywords: gui,example
Classifier: Programming Language :: Python :: 3
Classifier: License :: OSI Approved :: MIT License
Classifier: Operating System :: OS Independent
Requires-Python: >=3.6
License-File: LICENSE
Dynamic: author
Dynamic: author-email
Dynamic: classifier
Dynamic: description
Dynamic: description-content-type
Dynamic: home-page
Dynamic: keywords
Dynamic: license
Dynamic: requires-python
Dynamic: summary
